freexgraph/__init__.py
freexgraph/_version.py
freexgraph/freexgraph.py
freexgraph/standard_visitor.py
freexgraph/visitor.py
freexgraph-1.3.0.dist-info/LICENSE
freexgraph-1.3.0.dist-info/METADATA
freexgraph-1.3.0.dist-info/WHEEL
freexgraph-1.3.0.dist-info/top_level.txt
freexgraph-1.3.0.dist-info/RECORD
