Metadata-Version: 2.1
Name: freexgraph
Version: 1.3.0
Summary: An execution graph library
Home-page: https://github.com/FreeYourSoul/FreExGraph
Author: Quentin Balland
Author-email: ballandFyS@protonmail.com
License: UNKNOWN
Platform: UNKNOWN
Classifier: Programming Language :: Python :: 3
Classifier: License :: OSI Approved :: MIT License
Classifier: Operating System :: OS Independent
Requires-Python: >=3.6
License-File: LICENSE
Requires-Dist: tqdm
Requires-Dist: networkx
